aioimaplib/__init__.py
aioimaplib/aioimaplib.py
aioimaplib_hakiergrzonzo-1.0.1.dist-info/LICENSE.txt
aioimaplib_hakiergrzonzo-1.0.1.dist-info/METADATA
aioimaplib_hakiergrzonzo-1.0.1.dist-info/WHEEL
aioimaplib_hakiergrzonzo-1.0.1.dist-info/top_level.txt
aioimaplib_hakiergrzonzo-1.0.1.dist-info/RECORD
